aoirint_cv2videotools/__init__.py
aoirint_cv2videotools/fonts/ipaexg00401/IPA_Font_License_Agreement_v1.0.txt
aoirint_cv2videotools/fonts/ipaexg00401/Readme_ipaexg00401.txt
aoirint_cv2videotools/fonts/ipaexg00401/ipaexg.ttf
aoirint_cv2videotools/loader/FileLoader.py
aoirint_cv2videotools/loader/VideoLoader.py
aoirint_cv2videotools/loader/YouTubeLoader.py
aoirint_cv2videotools/loader/__init__.py
aoirint_cv2videotools/searcher/YouTubeLiveVideoSearcher.py
aoirint_cv2videotools/searcher/YouTubeVideoEntry.py
aoirint_cv2videotools/searcher/__init__.py
aoirint_cv2videotools/util/__init__.py
aoirint_cv2videotools/util/cv_put_text.py
aoirint_cv2videotools-0.0.1b7.dist-info/METADATA
aoirint_cv2videotools-0.0.1b7.dist-info/WHEEL
aoirint_cv2videotools-0.0.1b7.dist-info/top_level.txt
aoirint_cv2videotools-0.0.1b7.dist-info/RECORD
