Metadata-Version: 2.1
Name: aoirint-cv2videotools
Version: 0.0.1b7
Summary: OpenCV Video Tools
Home-page: https://github.com/aoirint/aoirint-cv2videotools/
Author: aoirint
License: MIT
Platform: UNKNOWN
Classifier: Programming Language :: Python :: 3
Classifier: Development Status :: 4 - Beta
Classifier: Environment :: Console
Classifier: Environment :: Web Environment
Classifier: Intended Audience :: Developers
Classifier: Operating System :: OS Independent
Classifier: License :: OSI Approved :: MIT License
Requires-Python: >=3.7
Requires-Dist: youtube-dl (>=2020.9.14)
Requires-Dist: opencv-python (>=4.4.0.42)
Requires-Dist: Pillow (>=7.2.0)
Requires-Dist: tqdm (>=4.49.0)
Requires-Dist: google-api-python-client (>=1.12.1)
Requires-Dist: python-dateutil (>=2.8.1)
Requires-Dist: configargparse (>=1.2.3)
Requires-Dist: PyYAML (>=5.3.1)
